MANIFEST.in
README.md
api_jwt.py
api_jwt_tests.py
conf.py
setup.py
api_jwt.egg-info/PKG-INFO
api_jwt.egg-info/SOURCES.txt
api_jwt.egg-info/dependency_links.txt
api_jwt.egg-info/requires.txt
api_jwt.egg-info/top_level.txt