Metadata-Version: 2.1
Name: api-jwt
Version: 1.2.2
Summary: Library for JWT encoding/decoding specifically adapted to use in APIs
Home-page: https://github.com/gregertw/api_jwt
Author: Greger Wedel
Author-email: greger@greger.io
License: Apache2
Platform: UNKNOWN
Classifier: Development Status :: 5 - Production/Stable
Classifier: Intended Audience :: Developers
Classifier: License :: OSI Approved :: Apache Software License
Classifier: Programming Language :: Python :: 3.6
Classifier: Programming Language :: Python :: 3.7
